cmp_ipproxy_lib/__init__.py
cmp_ipproxy_lib/config.yaml
cmp_ipproxy_lib/ip_proxy.py
cmp_ipproxy_lib/logging_config.yaml
cmp_ipproxy_lib/grpc_client/__init__.py
cmp_ipproxy_lib/grpc_generate/AgentFeedBackBucket_pb2.py
cmp_ipproxy_lib/grpc_generate/AgentFeedBackBucket_pb2_grpc.py
cmp_ipproxy_lib/grpc_generate/AgentFeedBack_pb2.py
cmp_ipproxy_lib/grpc_generate/AgentFeedBack_pb2_grpc.py
cmp_ipproxy_lib/grpc_generate/AgentFetchProxy_pb2.py
cmp_ipproxy_lib/grpc_generate/AgentFetchProxy_pb2_grpc.py
cmp_ipproxy_lib/grpc_generate/AgentHeartBeat_pb2.py
cmp_ipproxy_lib/grpc_generate/AgentHeartBeat_pb2_grpc.py
cmp_ipproxy_lib/grpc_generate/__init__.py
cmp_ipproxy_lib/grpc_service/__init__.py
cmp_ipproxy_lib/http_plugins/__init__.py
cmp_ipproxy_lib/http_plugins/agent_http_server/__init__.py
cmp_ipproxy_lib/http_plugins/agent_request/__init__.py
cmp_ipproxy_lib/http_plugins/agent_urllib_request/__init__.py
cmp_ipproxy_lib/util/ReportInfo.py
cmp_ipproxy_lib/util/__init__.py
cmp_ipproxy_lib/util/add_proxy.py
cmp_ipproxy_lib/util/global_dict.py
cmp_ipproxy_lib/util/rocketmq_producer.py
cmp_ipproxy_lib/util/setting_config.py
cmp_ipproxy_lib-0.0.1.dist-info/LICENSE
cmp_ipproxy_lib-0.0.1.dist-info/METADATA
cmp_ipproxy_lib-0.0.1.dist-info/WHEEL
cmp_ipproxy_lib-0.0.1.dist-info/top_level.txt
cmp_ipproxy_lib-0.0.1.dist-info/RECORD
